{
  "cs.AI": 2172,
  "cs.AR": 147,
  "cs.CC": 530,
  "cs.CE": 277,
  "cs.CG": 329,
  "cs.CL": 1738,
  "cs.CR": 1168,
  "cs.CV": 3702,
  "cs.CY": 667,
  "cs.DB": 383,
  "cs.DC": 899,
  "cs.DL": 231,
  "cs.DM": 651,
  "cs.DS": 1124,
  "cs.ET": 151,
  "cs.FL": 231,
  "cs.GL": 13,
  "cs.GR": 183,
  "cs.GT": 483,
  "cs.HC": 503,
  "cs.IR": 613,
  "cs.IT": 2297,
  "cs.LG": 5316,
  "cs.LO": 766,
  "cs.MA": 275,
  "cs.MM": 217,
  "cs.MS": 106,
  "cs.NA": 704,
  "cs.NE": 615,
  "cs.NI": 1022,
  "cs.OH": 129,
  "cs.OS": 40,
  "cs.PF": 174,
  "cs.PL": 349,
  "cs.RO": 904,
  "cs.SC": 121,
  "cs.SD": 380,
  "cs.SE": 593,
  "cs.SI": 909,
  "cs.SY": 1063,
  "econ.EM": 114,
  "econ.TH": 59,
  "eess.AS": 355,
  "eess.IV": 657,
  "eess.SP": 837,
  "eess.SY": 519,
  "math.AC": 665,
  "math.AG": 2769,
  "math.AP": 2963,
  "math.AT": 792,
  "math.CA": 1164,
  "math.CO": 3221,
  "math.CT": 408,
  "math.CV": 882,
  "math.DG": 2217,
  "math.DS": 1798,
  "math.FA": 1578,
  "math.GM": 200,
  "math.GN": 259,
  "math.GR": 1134,
  "math.GT": 1206,
  "math.HO": 181,
  "math.IT": 2297,
  "math.KT": 315,
  "math.LO": 659,
  "math.MG": 561,
  "math.MP": 4241,
  "math.NA": 1610,
  "math.NT": 2081,
  "math.OA": 679,
  "math.OC": 2021,
  "math.PR": 2818,
  "math.QA": 1064,
  "math.RA": 891,
  "math.RT": 1344,
  "math.SG": 485,
  "math.SP": 505,
  "math.ST": 1088,
  "astro-ph": 6801,
  "astro-ph.CO": 3519,
  "astro-ph.EP": 1353,
  "astro-ph.GA": 3018,
  "astro-ph.HE": 2735,
  "astro-ph.IM": 1314,
  "astro-ph.SR": 3041,
  "cond-mat": 917,
  "cond-mat.dis-nn": 1271,
  "cond-mat.mes-hall": 4754,
  "cond-mat.mtrl-sci": 4595,
  "cond-mat.other": 894,
  "cond-mat.quant-gas": 1075,
  "cond-mat.soft": 2100,
  "cond-mat.stat-mech": 4001,
  "cond-mat.str-el": 3917,
  "cond-mat.supr-con": 2398,
  "gr-qc": 5665,
  "hep-ex": 2855,
  "hep-lat": 1567,
  "hep-ph": 10129,
  "hep-th": 9294,
  "math-ph": 4241,
  "nlin.AO": 378,
  "nlin.CD": 886,
  "nlin.CG": 84,
  "nlin.PS": 522,
  "nlin.SI": 671,
  "nucl-ex": 1400,
  "nucl-th": 3200,
  "physics.acc-ph": 399,
  "physics.ao-ph": 290,
  "physics.app-ph": 661,
  "physics.atm-clus": 148,
  "physics.atom-ph": 1112,
  "physics.bio-ph": 771,
  "physics.chem-ph": 1024,
  "physics.class-ph": 455,
  "physics.comp-ph": 1049,
  "physics.ed-ph": 192,
  "physics.flu-dyn": 1259,
  "physics.gen-ph": 610,
  "physics.geo-ph": 324,
  "physics.hist-ph": 252,
  "physics.ins-det": 1027,
  "physics.med-ph": 288,
  "physics.optics": 2167,
  "physics.plasm-ph": 800,
  "physics.pop-ph": 128,
  "physics.soc-ph": 1139,
  "physics.space-ph": 292,
  "quant-ph": 7310,
  "q-bio.BM": 272,
  "q-bio.CB": 116,
  "q-bio.GN": 158,
  "q-bio.MN": 203,
  "q-bio.NC": 433,
  "q-bio.OT": 64,
  "q-bio.PE": 587,
  "q-bio.SC": 97,
  "q-bio.TO": 112,
  "q-fin.GN": 142,
  "q-fin.PM": 84,
  "q-fin.PR": 106,
  "q-fin.RM": 106,
  "q-fin.ST": 176,
  "q-fin.TR": 83,
  "stat.ME": 1065,
  "stat.ML": 3167,
  "stat.OT": 61,
  "stat.TH": 1088,
  "Medicine and Health": 202,
  "Information Science": 200,
  "Chemistry": 93,
  "Virology": 89,
  "Environmental Sciences": 39,
  "nolabel": 1294
}